kgraphlang/__init__.py
kgraphlang/kgraph_infer.py
kgraphlang/config/__init__.py
kgraphlang/config/reasoner_config.py
kgraphlang/filter_infer/__init__.py
kgraphlang/filter_infer/filter_predicate.py
kgraphlang/kgraphservice_infer/__init__.py
kgraphlang/kgraphservice_infer/kgraphservice_infer.py
kgraphlang/kgraphservice_infer/metaql_base_predicate.py
kgraphlang/kgraphservice_infer/metaql_infer_base_impl.py
kgraphlang/kgraphservice_infer/metaql_infer_merge_impl.py
kgraphlang/kgraphservice_infer/metaql_merge_predicate.py
kgraphlang/logic_infer/__init__.py
kgraphlang/logic_infer/ergoai_infer_impl.py
kgraphlang/logic_infer/logic_infer.py
kgraphlang/parser/__init__.py
kgraphlang/parser/kgraph_infer_parser.py
kgraphlang/predicate/__init__.py
kgraphlang/predicate/kgraph_predicate.py
kgraphlang-0.0.9.dist-info/LICENSE
kgraphlang-0.0.9.dist-info/METADATA
kgraphlang-0.0.9.dist-info/WHEEL
kgraphlang-0.0.9.dist-info/top_level.txt
kgraphlang-0.0.9.dist-info/RECORD
